endee/__init__.py
endee/crypto.py
endee/endee.py
endee/exceptions.py
endee/index.py
endee/user.py
endee/utils.py
endee-0.1.5.dist-info/licenses/LICENSE
endee-0.1.5.dist-info/METADATA
endee-0.1.5.dist-info/WHEEL
endee-0.1.5.dist-info/top_level.txt
endee-0.1.5.dist-info/RECORD
