Metadata-Version: 2.4
Name: endee
Version: 0.1.5
Summary: Enddee is the Next-Generation Vector Database for Scalable, High-Performance AI
Home-page: https://endee.io
Author: Endee Labs
Author-email: dev@endee.io
Classifier: Programming Language :: Python :: 3
Classifier: License :: OSI Approved :: MIT License
Classifier: Operating System :: OS Independent
Requires-Python: >=3.6
License-File: LICENSE
Requires-Dist: requests>=2.28.0
Requires-Dist: numpy>=2.2.4
Requires-Dist: msgpack>=1.1.0
Requires-Dist: cryptography>=41.0.0
Dynamic: author
Dynamic: author-email
Dynamic: classifier
Dynamic: description
Dynamic: description-content-type
Dynamic: home-page
Dynamic: license-file
Dynamic: requires-dist
Dynamic: requires-python
Dynamic: summary
